LICENSE
MANIFEST.in
README.rst
setup.py
dj_sso_server2.egg-info/PKG-INFO
dj_sso_server2.egg-info/SOURCES.txt
dj_sso_server2.egg-info/dependency_links.txt
dj_sso_server2.egg-info/requires.txt
dj_sso_server2.egg-info/top_level.txt
djssoserver/__init__.py
djssoserver/admin.py
djssoserver/apps.py
djssoserver/models.py
djssoserver/sso.py
djssoserver/tests.py
djssoserver/urls.py
djssoserver/utility.py
djssoserver/views.py
djssoserver/migrations/0001_initial.py
djssoserver/migrations/__init__.py
djssoserver/templates/djssoserver/403.html
djssoserver/templates/djssoserver/ssologin.html
example/djssoserverapp/Procfile
example/djssoserverapp/initial_data.json
example/djssoserverapp/manage.py
example/djssoserverapp/requirements.txt
example/djssoserverapp/djssoserverapp/__init__.py
example/djssoserverapp/djssoserverapp/settings.py
example/djssoserverapp/djssoserverapp/urls.py
example/djssoserverapp/djssoserverapp/views.py
example/djssoserverapp/djssoserverapp/wsgi.py
example/djssoserverapp/templates/index.html
example/djssoserverapp/templates/registration/logged_out.html
example/djssoserverapp/templates/registration/login.html